geomanager/__init__.py
geomanager/admin.py
geomanager/apps.py
geomanager/blocks.py
geomanager/constants.py
geomanager/decorators.py
geomanager/errors.py
geomanager/fields.py
geomanager/helpers.py
geomanager/panels.py
geomanager/settings.py
geomanager/storage.py
geomanager/tests.py
geomanager/urls.py
geomanager/validators.py
geomanager/wagtail_hooks.py
geomanager/widgets.py
geomanager/admin/__init__.py
geomanager/admin/base.py
geomanager/admin/boundary.py
geomanager/admin/category.py
geomanager/admin/dataset.py
geomanager/admin/mbt_source.py
geomanager/admin/metadata.py
geomanager/admin/raster_file.py
geomanager/admin/raster_style.py
geomanager/admin/raster_tile.py
geomanager/admin/vector_file.py
geomanager/admin/vector_tile.py
geomanager/admin/wms.py
geomanager/forms/__init__.py
geomanager/forms/aoi.py
geomanager/forms/boundary.py
geomanager/forms/geomanager_user_profile.py
geomanager/forms/raster_file.py
geomanager/forms/raster_style.py
geomanager/forms/vector_file.py
geomanager/forms/vector_table.py
geomanager/locale/am/LC_MESSAGES/django.po
geomanager/locale/ar/LC_MESSAGES/django.po
geomanager/locale/en/LC_MESSAGES/django.po
geomanager/locale/es/LC_MESSAGES/django.po
geomanager/locale/fr/LC_MESSAGES/django.po
geomanager/locale/sw/LC_MESSAGES/django.po
geomanager/management/__init__.py
geomanager/management/commands/__init__.py
geomanager/management/commands/ingest_geomanager_raster.py
geomanager/management/commands/initialize_geomanager.py
geomanager/management/commands/process_geomanager_layer_directory.py
geomanager/migrations/0001_initial.py
geomanager/migrations/0001_squashed_0024_rastertilelayer_get_time_from_tile_json_and_more.py
geomanager/migrations/0002_geomanagersettings_logo_and_more.py
geomanager/migrations/0003_alter_colorvalue_label_alter_colorvalue_threshold_and_more.py
geomanager/migrations/0004_alter_dataset_can_clip.py
geomanager/migrations/0005_delete_countryboundary_and_more.py
geomanager/migrations/0006_stationsettings.py
geomanager-0.5.8.dist-info/licenses/LICENSE
geomanager-0.5.8.dist-info/METADATA
geomanager-0.5.8.dist-info/WHEEL
geomanager-0.5.8.dist-info/top_level.txt
geomanager-0.5.8.dist-info/RECORD
