Metadata-Version: 2.4
Name: geomanager
Version: 0.5.8
Summary: Wagtail based Geospatial Data Manager
Home-page: https://github.com/erick-otenyo/geomanager
Author: Erick Otenyo
Author-email: otenyo.erick@gmail.com
License: MIT
Classifier: Development Status :: 4 - Beta
Classifier: Environment :: Web Environment
Classifier: Intended Audience :: Developers
Classifier: License :: OSI Approved :: MIT License
Classifier: Operating System :: OS Independent
Classifier: Programming Language :: Python :: 3 :: Only
Classifier: Programming Language :: Python :: 3.9
Classifier: Programming Language :: Python :: Implementation :: CPython
Classifier: Topic :: Software Development :: Libraries :: Application Frameworks
Classifier: Topic :: Software Development :: Libraries :: Python Modules
Requires-Python: >=3.9
License-File: LICENSE
Requires-Dist: wagtail>=6.3.2
Requires-Dist: wagtail-modeladmin>=2.1.0
Requires-Dist: adm-boundary-manager>=0.2.5
Requires-Dist: django_extensions>=3.2.1
Requires-Dist: wagtail_color_panel>=1.4.1
Requires-Dist: wagtail-font-awesome-svg>=1.0.1
Requires-Dist: django_json_widget>=1.1.1
Requires-Dist: django_nextjs==2.4.0
Requires-Dist: django-allauth>=0.54.0
Requires-Dist: django-large-image>=0.10.0
Requires-Dist: large-image-source-rasterio>=1.22.2
Requires-Dist: large-image-source-pil>=1.22.2
Requires-Dist: django-filter>=22.1
Requires-Dist: cftime>=1.6.2
Requires-Dist: netCDF4>=1.6.3
Requires-Dist: rasterio>=1.3.6
Requires-Dist: rio-cogeo>=3.5.1
Requires-Dist: xarray>=2023.3.0
Requires-Dist: rioxarray>=0.14.0
Requires-Dist: shapely>=2.0.1
Requires-Dist: djangorestframework-simplejwt>=5.2.2
Requires-Dist: wagtail-humanitarian-icons>=2.0.0
Requires-Dist: wagtail-icon-chooser>=0.3.1
Requires-Dist: matplotlib>=3.7.1
Requires-Dist: CairoSVG>=2.7.0
Requires-Dist: wagtail-cache>=2.5.1
Requires-Dist: mercantile>=1.2.1
Dynamic: license-file
